test_sdk/__init__.py
test_sdk/sdk.py
test_sdk/hooks/__init__.py
test_sdk/hooks/hook.py
test_sdk/models/__init__.py
test_sdk/models/base.py
test_sdk/models/pet.py
test_sdk/models/utils/cast_models.py
test_sdk/models/utils/json_map.py
test_sdk/net/__init__.py
test_sdk/net/environment/__init__.py
test_sdk/net/environment/environment.py
test_sdk/net/headers/__init__.py
test_sdk/net/headers/base_header.py
test_sdk/net/request_chain/__init__.py
test_sdk/net/request_chain/request_chain.py
test_sdk/net/request_chain/handlers/__init__.py
test_sdk/net/request_chain/handlers/base_handler.py
test_sdk/net/request_chain/handlers/hook_handler.py
test_sdk/net/request_chain/handlers/http_handler.py
test_sdk/net/request_chain/handlers/retry_handler.py
test_sdk/net/transport/__init__.py
test_sdk/net/transport/request.py
test_sdk/net/transport/request_error.py
test_sdk/net/transport/response.py
test_sdk/net/transport/serializer.py
test_sdk/net/transport/utils.py
test_sdk/services/__init__.py
test_sdk/services/pets.py
test_sdk/services/utils/base_service.py
test_sdk/services/utils/default_headers.py
test_sdk/services/utils/validator.py
DC_Test_petstore_sdk-6.9.1.dist-info/METADATA
DC_Test_petstore_sdk-6.9.1.dist-info/WHEEL
DC_Test_petstore_sdk-6.9.1.dist-info/top_level.txt
DC_Test_petstore_sdk-6.9.1.dist-info/RECORD
