Metadata-Version: 2.1
Name: DC-Test-petstore-sdk
Version: 6.9.1
Requires-Python: >=3.7
Requires-Dist: requests >=2.31.0
